Topsis/TOPSIS.py
Topsis/__init__.py
TOPSIS_Pratyaksh_Verma_101703402-0.0.1.dist-info/LICENSE
TOPSIS_Pratyaksh_Verma_101703402-0.0.1.dist-info/METADATA
TOPSIS_Pratyaksh_Verma_101703402-0.0.1.dist-info/WHEEL
TOPSIS_Pratyaksh_Verma_101703402-0.0.1.dist-info/top_level.txt
TOPSIS_Pratyaksh_Verma_101703402-0.0.1.dist-info/RECORD
