Metadata-Version: 2.1
Name: TOPSIS-Pratyaksh-Verma-101703402
Version: 0.0.1
Summary: TOPSIS for PyPi
Home-page: https://github.com/pratyakshverma/TOPSIS
Author: Pratyaksh Verma
Author-email: pverma_be17@thapar.edu
License: UNKNOWN
Platform: UNKNOWN
Classifier: Programming Language :: Python :: 3
Classifier: License :: OSI Approved :: MIT License
Classifier: Operating System :: OS Independent
Requires-Python: >=3.6
